<?xml version="1.0" encoding="utf-8"?><helpItems xmlns="http://msh" schema="maml">
<command:command xmlns:maml="http://schemas.microsoft.com/maml/2004/10" xmlns:command="http://schemas.microsoft.com/maml/dev/command/2004/10" xmlns:dev="http://schemas.microsoft.com/maml/dev/2004/10">
<!--Generated by PS Cmdlet Help Editor-->
	<command:details>
		<command:name>Get-BuildConfigurations</command:name>
		<maml:description>
			<maml:para></maml:para>
		</maml:description>
		<maml:copyright>
			<maml:para />
		</maml:copyright>
		<command:verb>Get</command:verb>
		<command:noun>BuildConfigurations</command:noun>
		<dev:version />
	</command:details>
	<maml:description>
	<!--This is the Description section-->
		<maml:para>Displays the available build configurations from the active or the specified project.</maml:para>
	</maml:description>
	<command:syntax>
		<command:syntaxItem>
			<maml:name>Get-BuildConfigurations</maml:name>
			<command:parameter required="false" variableLength="false" globbing="false" pipelineInput="false" position="named">
				<maml:name>Project</maml:name>
				<maml:description>
					<maml:para>The name of the project to get build configurations from.</maml:para>
				</maml:description>
				<command:parameterValue required="true" variableLength="false">String</command:parameterValue>
			</command:parameter>
		</command:syntaxItem>
	</command:syntax>
	<command:parameters>
		<command:parameter required="false" variableLength="false" globbing="false" pipelineInput="false" position="named">
			<maml:name>Project</maml:name>
			<maml:description>
				<maml:para>The name of the project to get build configurations from.</maml:para>
			</maml:description>
			<command:parameterValue required="true" variableLength="false">String</command:parameterValue>
			<dev:type>
				<maml:name>String</maml:name>
				<maml:uri/>
			</dev:type>
			<dev:defaultValue></dev:defaultValue>
		</command:parameter>
	</command:parameters>
	<command:inputTypes>
		<command:inputType>
			<dev:type>
				<maml:name></maml:name>
				<maml:uri/>
				<maml:description>
					<maml:para></maml:para>
				</maml:description>
			</dev:type>
			<maml:description></maml:description>
		</command:inputType>
	</command:inputTypes>
	<command:returnValues>
		<command:returnValue>
			<dev:type>
				<maml:name></maml:name>
				<maml:uri/>
				<maml:description>
					<maml:para></maml:para>
				</maml:description>
			</dev:type>
			<maml:description></maml:description>
	</command:returnValue>
		</command:returnValues>
	<command:terminatingErrors></command:terminatingErrors>
	<command:nonTerminatingErrors></command:nonTerminatingErrors>
	<maml:alertSet>
		<maml:title></maml:title>
		<maml:alert>
			<maml:para></maml:para>
		</maml:alert>
	</maml:alertSet>
	<command:examples>
		<command:example>
			<maml:title>--------------  Example 1  --------------</maml:title>
			<maml:introduction>
				<maml:para></maml:para>
			</maml:introduction>
			<dev:code>PS C:\&gt; Get-BuildConfigurations</dev:code>
			<dev:remarks>
				<maml:para>Displays all build configurations of the active project.</maml:para>
			</dev:remarks>
			<command:commandLines>
				<command:commandLine>
					<command:commandText>Project1_Test
Project1_Production</command:commandText>
				</command:commandLine>
			</command:commandLines>
		</command:example>
		<command:example>
			<maml:title>--------------  Example 2  --------------</maml:title>
			<maml:introduction>
				<maml:para></maml:para>
			</maml:introduction>
			<dev:code>PS C:\&gt; Get-BuildConfigurations -Project Project1</dev:code>
			<dev:remarks>
				<maml:para>Displays all build configurations of Project1.</maml:para>
			</dev:remarks>
			<command:commandLines>
				<command:commandLine>
					<command:commandText>Project1_Test
Project1_Production</command:commandText>
				</command:commandLine>
			</command:commandLines>
		</command:example>
	</command:examples>
	<maml:relatedLinks>
	</maml:relatedLinks>
</command:command>
<command:command xmlns:maml="http://schemas.microsoft.com/maml/2004/10" xmlns:command="http://schemas.microsoft.com/maml/dev/command/2004/10" xmlns:dev="http://schemas.microsoft.com/maml/dev/2004/10">
<!--Generated by PS Cmdlet Help Editor-->
	<command:details>
		<command:name>Get-BuildTags</command:name>
		<maml:description>
			<maml:para></maml:para>
		</maml:description>
		<maml:copyright>
			<maml:para />
		</maml:copyright>
		<command:verb>Get</command:verb>
		<command:noun>BuildTags</command:noun>
		<dev:version />
	</command:details>
	<maml:description>
	<!--This is the Description section-->
		<maml:para>Displays all tags of the active project.</maml:para>
	</maml:description>
	<command:syntax>
		<command:syntaxItem>
			<maml:name>Get-BuildTags</maml:name>
			<command:parameter required="false" variableLength="false" globbing="false" pipelineInput="false" position="named">
				<maml:name>BuildConfiguration</maml:name>
				<maml:description>
					<maml:para>The build configuration to get tags from.</maml:para>
				</maml:description>
				<command:parameterValue required="true" variableLength="false">String</command:parameterValue>
			</command:parameter>
		</command:syntaxItem>
	</command:syntax>
	<command:parameters>
		<command:parameter required="true" variableLength="false" globbing="false" pipelineInput="false" position="named">
			<maml:name>BuildConfiguration</maml:name>
			<maml:description>
				<maml:para>The build configuration to get tags from.</maml:para>
			</maml:description>
			<command:parameterValue required="true" variableLength="false">String</command:parameterValue>
			<dev:type>
				<maml:name>String</maml:name>
				<maml:uri/>
			</dev:type>
			<dev:defaultValue></dev:defaultValue>
		</command:parameter>
	</command:parameters>
	<command:inputTypes>
		<command:inputType>
			<dev:type>
				<maml:name></maml:name>
				<maml:uri/>
				<maml:description>
					<maml:para></maml:para>
				</maml:description>
			</dev:type>
			<maml:description></maml:description>
		</command:inputType>
	</command:inputTypes>
	<command:returnValues>
		<command:returnValue>
			<dev:type>
				<maml:name></maml:name>
				<maml:uri/>
				<maml:description>
					<maml:para></maml:para>
				</maml:description>
			</dev:type>
			<maml:description></maml:description>
	</command:returnValue>
		</command:returnValues>
	<command:terminatingErrors></command:terminatingErrors>
	<command:nonTerminatingErrors></command:nonTerminatingErrors>
	<maml:alertSet>
		<maml:title></maml:title>
		<maml:alert>
			<maml:para></maml:para>
		</maml:alert>
	</maml:alertSet>
	<command:examples>
		<command:example>
			<maml:title>--------------  Example 1  --------------</maml:title>
			<maml:introduction>
				<maml:para></maml:para>
			</maml:introduction>
			<dev:code>PS C:\&gt; Get-BuildTags</dev:code>
			<dev:remarks>
				<maml:para>Displays build tags from the active project and the default build configuration</maml:para>
			</dev:remarks>
			<command:commandLines>
				<command:commandLine>
					<command:commandText>v2.0
v2.1</command:commandText>
				</command:commandLine>
			</command:commandLines>
		</command:example>
		<command:example>
			<maml:title>--------------  Example 2  --------------</maml:title>
			<maml:introduction>
				<maml:para></maml:para>
			</maml:introduction>
			<dev:code>PS C:\&gt; Get-BuildTags -BuildConfiguration Test</dev:code>
			<dev:remarks>
				<maml:para>Displays build tags from the active project and build configuration Test.</maml:para>
			</dev:remarks>
			<command:commandLines>
				<command:commandLine>
					<command:commandText>v2.0
v2.1</command:commandText>
				</command:commandLine>
			</command:commandLines>
		</command:example>
	</command:examples>
	<maml:relatedLinks>
	</maml:relatedLinks>
</command:command>
<command:command xmlns:maml="http://schemas.microsoft.com/maml/2004/10" xmlns:command="http://schemas.microsoft.com/maml/dev/command/2004/10" xmlns:dev="http://schemas.microsoft.com/maml/dev/2004/10">
<!--Generated by PS Cmdlet Help Editor-->
	<command:details>
		<command:name>Get-Projects</command:name>
		<maml:description>
			<maml:para></maml:para>
		</maml:description>
		<maml:copyright>
			<maml:para />
		</maml:copyright>
		<command:verb>Get</command:verb>
		<command:noun>Projects</command:noun>
		<dev:version />
	</command:details>
	<maml:description>
	<!--This is the Description section-->
		<maml:para>Displays all projects.</maml:para>
	</maml:description>
	<command:syntax>
		<command:syntaxItem>
			<maml:name>Get-Projects</maml:name>
		</command:syntaxItem>
	</command:syntax>
	<command:parameters>	</command:parameters>
	<command:inputTypes>
		<command:inputType>
			<dev:type>
				<maml:name></maml:name>
				<maml:uri/>
				<maml:description>
					<maml:para></maml:para>
				</maml:description>
			</dev:type>
			<maml:description></maml:description>
		</command:inputType>
	</command:inputTypes>
	<command:returnValues>
		<command:returnValue>
			<dev:type>
				<maml:name></maml:name>
				<maml:uri/>
				<maml:description>
					<maml:para></maml:para>
				</maml:description>
			</dev:type>
			<maml:description></maml:description>
	</command:returnValue>
		</command:returnValues>
	<command:terminatingErrors></command:terminatingErrors>
	<command:nonTerminatingErrors></command:nonTerminatingErrors>
	<maml:alertSet>
		<maml:title></maml:title>
		<maml:alert>
			<maml:para></maml:para>
		</maml:alert>
	</maml:alertSet>
	<command:examples>
		<command:example>
			<maml:title>--------------  Example 1  --------------</maml:title>
			<maml:introduction>
				<maml:para></maml:para>
			</maml:introduction>
			<dev:code>PS C:\&gt; Get-Projects</dev:code>
			<dev:remarks>
				<maml:para>Displays all projects.</maml:para>
			</dev:remarks>
			<command:commandLines>
				<command:commandLine>
					<command:commandText>Project1
Project2</command:commandText>
				</command:commandLine>
			</command:commandLines>
		</command:example>
	</command:examples>
	<maml:relatedLinks>
	</maml:relatedLinks>
</command:command>
<command:command xmlns:maml="http://schemas.microsoft.com/maml/2004/10" xmlns:command="http://schemas.microsoft.com/maml/dev/command/2004/10" xmlns:dev="http://schemas.microsoft.com/maml/dev/2004/10">
<!--Generated by PS Cmdlet Help Editor-->
	<command:details>
		<command:name>Save-BuildArtifacts</command:name>
		<maml:description>
			<maml:para></maml:para>
		</maml:description>
		<maml:copyright>
			<maml:para />
		</maml:copyright>
		<command:verb>Save</command:verb>
		<command:noun>BuildArtifacts</command:noun>
		<dev:version />
	</command:details>
	<maml:description>
	<!--This is the Description section-->
		<maml:para>Downloads all artifacts from a build configuration to a specific local path.</maml:para>
	</maml:description>
	<command:syntax>
		<command:syntaxItem>
			<maml:name>Save-BuildArtifacts</maml:name>
			<command:parameter required="true" variableLength="false" globbing="false" pipelineInput="false" position="named">
				<maml:name>BuildConfiguration</maml:name>
				<maml:description>
					<maml:para>The build configuration to download from.</maml:para>
				</maml:description>
				<command:parameterValue required="true" variableLength="false">String</command:parameterValue>
			</command:parameter>
			<command:parameter required="false" variableLength="false" globbing="false" pipelineInput="false" position="named">
				<maml:name>Tag</maml:name>
				<maml:description>
					<maml:para>The build tag to download.</maml:para>
				</maml:description>
				<command:parameterValue required="true" variableLength="false">String</command:parameterValue>
			</command:parameter>
		</command:syntaxItem>
	</command:syntax>
	<command:parameters>
		<command:parameter required="true" variableLength="false" globbing="false" pipelineInput="false" position="named">
			<maml:name>BuildConfiguration</maml:name>
			<maml:description>
				<maml:para>The build configuration to download from.</maml:para>
			</maml:description>
			<command:parameterValue required="true" variableLength="false">String</command:parameterValue>
			<dev:type>
				<maml:name>String</maml:name>
				<maml:uri/>
			</dev:type>
			<dev:defaultValue></dev:defaultValue>
		</command:parameter>
		<command:parameter required="false" variableLength="false" globbing="false" pipelineInput="false" position="named">
			<maml:name>Tag</maml:name>
			<maml:description>
				<maml:para>The build tag to download.</maml:para>
			</maml:description>
			<command:parameterValue required="true" variableLength="false">String</command:parameterValue>
			<dev:type>
				<maml:name>String</maml:name>
				<maml:uri/>
			</dev:type>
			<dev:defaultValue></dev:defaultValue>
		</command:parameter>
	</command:parameters>
	<command:inputTypes>
		<command:inputType>
			<dev:type>
				<maml:name></maml:name>
				<maml:uri/>
				<maml:description>
					<maml:para></maml:para>
				</maml:description>
			</dev:type>
			<maml:description></maml:description>
		</command:inputType>
	</command:inputTypes>
	<command:returnValues>
		<command:returnValue>
			<dev:type>
				<maml:name></maml:name>
				<maml:uri/>
				<maml:description>
					<maml:para></maml:para>
				</maml:description>
			</dev:type>
			<maml:description></maml:description>
	</command:returnValue>
		</command:returnValues>
	<command:terminatingErrors></command:terminatingErrors>
	<command:nonTerminatingErrors></command:nonTerminatingErrors>
	<maml:alertSet>
		<maml:title></maml:title>
		<maml:alert>
			<maml:para></maml:para>
		</maml:alert>
	</maml:alertSet>
	<command:examples>
		<command:example>
			<maml:title>--------------  Example 1  --------------</maml:title>
			<maml:introduction>
				<maml:para></maml:para>
			</maml:introduction>
			<dev:code>PS C:\&gt; Save-BuildArtifacts -Tag v2.1</dev:code>
			<dev:remarks>
				<maml:para>Downloads all artifacts from build tagged as v2.1.</maml:para>
			</dev:remarks>
			<command:commandLines>
				<command:commandLine>
					<command:commandText></command:commandText>
				</command:commandLine>
			</command:commandLines>
		</command:example>
		<command:example>
			<maml:title>--------------  Example 2  --------------</maml:title>
			<maml:introduction>
				<maml:para></maml:para>
			</maml:introduction>
			<dev:code>PS C:\&gt; Save-BuildArtifacts -BuildConfiguration Test -Tag v2.1</dev:code>
			<dev:remarks>
				<maml:para>Downloads all artifacts tagged with v2.1 in build configuration Test.</maml:para>
			</dev:remarks>
			<command:commandLines>
				<command:commandLine>
					<command:commandText></command:commandText>
				</command:commandLine>
			</command:commandLines>
		</command:example>
	</command:examples>
	<maml:relatedLinks>
	</maml:relatedLinks>
</command:command>
<command:command xmlns:maml="http://schemas.microsoft.com/maml/2004/10" xmlns:command="http://schemas.microsoft.com/maml/dev/command/2004/10" xmlns:dev="http://schemas.microsoft.com/maml/dev/2004/10">
<!--Generated by PS Cmdlet Help Editor-->
	<command:details>
		<command:name>Select-BuildServer</command:name>
		<maml:description>
			<maml:para></maml:para>
		</maml:description>
		<maml:copyright>
			<maml:para />
		</maml:copyright>
		<command:verb>Select</command:verb>
		<command:noun>BuildServer</command:noun>
		<dev:version />
	</command:details>
	<maml:description>
	<!--This is the Description section-->
		<maml:para>Sets up settings for connecting to the build server.</maml:para>
	</maml:description>
	<command:syntax>
		<command:syntaxItem>
			<maml:name>Select-BuildServer</maml:name>
			<command:parameter required="true" variableLength="false" globbing="false" pipelineInput="false" position="named">
				<maml:name>ApiUri</maml:name>
				<maml:description>
					<maml:para>The URI to the build server.</maml:para>
				</maml:description>
				<command:parameterValue required="true" variableLength="false">String</command:parameterValue>
			</command:parameter>
			<command:parameter required="true" variableLength="false" globbing="false" pipelineInput="false" position="named">
				<maml:name>ApiUserName</maml:name>
				<maml:description>
					<maml:para>The username to authenticate on the build server.</maml:para>
				</maml:description>
				<command:parameterValue required="true" variableLength="false">String</command:parameterValue>
			</command:parameter>
			<command:parameter required="true" variableLength="false" globbing="false" pipelineInput="false" position="named">
				<maml:name>ApiPassword</maml:name>
				<maml:description>
					<maml:para>The password to authenticate on the build server.</maml:para>
				</maml:description>
				<command:parameterValue required="true" variableLength="false">String</command:parameterValue>
			</command:parameter>
			<command:parameter required="true" variableLength="false" globbing="false" pipelineInput="false" position="named">
				<maml:name>LocalDeployPath</maml:name>
				<maml:description>
					<maml:para>The base path to download build artifacts to.</maml:para>
				</maml:description>
				<command:parameterValue required="true" variableLength="false">String</command:parameterValue>
			</command:parameter>
		</command:syntaxItem>
	</command:syntax>
	<command:parameters>
		<command:parameter required="true" variableLength="false" globbing="false" pipelineInput="false" position="named">
			<maml:name>ApiUri</maml:name>
			<maml:description>
				<maml:para>The URI to the build server.</maml:para>
			</maml:description>
			<command:parameterValue required="true" variableLength="false">String</command:parameterValue>
			<dev:type>
				<maml:name>String</maml:name>
				<maml:uri/>
			</dev:type>
			<dev:defaultValue></dev:defaultValue>
		</command:parameter>
		<command:parameter required="true" variableLength="false" globbing="false" pipelineInput="false" position="named">
			<maml:name>ApiUserName</maml:name>
			<maml:description>
				<maml:para>The username to authenticate on the build server.</maml:para>
			</maml:description>
			<command:parameterValue required="true" variableLength="false">String</command:parameterValue>
			<dev:type>
				<maml:name>String</maml:name>
				<maml:uri/>
			</dev:type>
			<dev:defaultValue></dev:defaultValue>
		</command:parameter>
		<command:parameter required="true" variableLength="false" globbing="false" pipelineInput="false" position="named">
			<maml:name>ApiPassword</maml:name>
			<maml:description>
				<maml:para>The password to authenticate on the build server.</maml:para>
			</maml:description>
			<command:parameterValue required="true" variableLength="false">String</command:parameterValue>
			<dev:type>
				<maml:name>String</maml:name>
				<maml:uri/>
			</dev:type>
			<dev:defaultValue></dev:defaultValue>
		</command:parameter>
		<command:parameter required="true" variableLength="false" globbing="false" pipelineInput="false" position="named">
			<maml:name>LocalDeployPath</maml:name>
			<maml:description>
				<maml:para>The base path to download build artifacts to.</maml:para>
			</maml:description>
			<command:parameterValue required="true" variableLength="false">String</command:parameterValue>
			<dev:type>
				<maml:name>String</maml:name>
				<maml:uri/>
			</dev:type>
			<dev:defaultValue></dev:defaultValue>
		</command:parameter>
	</command:parameters>
	<command:inputTypes>
		<command:inputType>
			<dev:type>
				<maml:name></maml:name>
				<maml:uri/>
				<maml:description>
					<maml:para></maml:para>
				</maml:description>
			</dev:type>
			<maml:description></maml:description>
		</command:inputType>
	</command:inputTypes>
	<command:returnValues>
		<command:returnValue>
			<dev:type>
				<maml:name></maml:name>
				<maml:uri/>
				<maml:description>
					<maml:para></maml:para>
				</maml:description>
			</dev:type>
			<maml:description></maml:description>
	</command:returnValue>
		</command:returnValues>
	<command:terminatingErrors></command:terminatingErrors>
	<command:nonTerminatingErrors></command:nonTerminatingErrors>
	<maml:alertSet>
		<maml:title></maml:title>
		<maml:alert>
			<maml:para></maml:para>
		</maml:alert>
	</maml:alertSet>
	<command:examples>
		<command:example>
			<maml:title>--------------  Example 1  --------------</maml:title>
			<maml:introduction>
				<maml:para></maml:para>
			</maml:introduction>
			<dev:code>PS C:\&gt; Select-BuildServer -AU http://mybuildserver/ -U usr -P &apos;pwd&apos; -DP C:\Deploy -E Test</dev:code>
			<dev:remarks>
				<maml:para>Configures connection to api.</maml:para>
			</dev:remarks>
			<command:commandLines>
				<command:commandLine>
					<command:commandText></command:commandText>
				</command:commandLine>
			</command:commandLines>
		</command:example>
	</command:examples>
	<maml:relatedLinks>
	</maml:relatedLinks>
</command:command>
<command:command xmlns:maml="http://schemas.microsoft.com/maml/2004/10" xmlns:command="http://schemas.microsoft.com/maml/dev/command/2004/10" xmlns:dev="http://schemas.microsoft.com/maml/dev/2004/10">
<!--Generated by PS Cmdlet Help Editor-->
	<command:details>
		<command:name>Select-Project</command:name>
		<maml:description>
			<maml:para></maml:para>
		</maml:description>
		<maml:copyright>
			<maml:para />
		</maml:copyright>
		<command:verb>Select</command:verb>
		<command:noun>Project</command:noun>
		<dev:version />
	</command:details>
	<maml:description>
	<!--This is the Description section-->
		<maml:para>Sets the active project.</maml:para>
	</maml:description>
	<command:syntax>
		<command:syntaxItem>
			<maml:name>Select-Project</maml:name>
			<command:parameter required="true" variableLength="false" globbing="false" pipelineInput="false" position="named">
				<maml:name>Name</maml:name>
				<maml:description>
					<maml:para>The name of the project to set as the active project.</maml:para>
				</maml:description>
				<command:parameterValue required="true" variableLength="false">String</command:parameterValue>
			</command:parameter>
		</command:syntaxItem>
	</command:syntax>
	<command:parameters>
		<command:parameter required="true" variableLength="false" globbing="false" pipelineInput="false" position="named">
			<maml:name>Name</maml:name>
			<maml:description>
				<maml:para>The name of the project to set as the active project.</maml:para>
			</maml:description>
			<command:parameterValue required="true" variableLength="false">String</command:parameterValue>
			<dev:type>
				<maml:name>String</maml:name>
				<maml:uri/>
			</dev:type>
			<dev:defaultValue></dev:defaultValue>
		</command:parameter>
	</command:parameters>
	<command:inputTypes>
		<command:inputType>
			<dev:type>
				<maml:name></maml:name>
				<maml:uri/>
				<maml:description>
					<maml:para></maml:para>
				</maml:description>
			</dev:type>
			<maml:description></maml:description>
		</command:inputType>
	</command:inputTypes>
	<command:returnValues>
		<command:returnValue>
			<dev:type>
				<maml:name></maml:name>
				<maml:uri/>
				<maml:description>
					<maml:para></maml:para>
				</maml:description>
			</dev:type>
			<maml:description></maml:description>
	</command:returnValue>
		</command:returnValues>
	<command:terminatingErrors></command:terminatingErrors>
	<command:nonTerminatingErrors></command:nonTerminatingErrors>
	<maml:alertSet>
		<maml:title></maml:title>
		<maml:alert>
			<maml:para></maml:para>
		</maml:alert>
	</maml:alertSet>
	<command:examples>
		<command:example>
			<maml:title>--------------  Example 1  --------------</maml:title>
			<maml:introduction>
				<maml:para></maml:para>
			</maml:introduction>
			<dev:code>PS C:\&gt; Select-Project -N Project1</dev:code>
			<dev:remarks>
				<maml:para>Sets Project1 as the active project.</maml:para>
			</dev:remarks>
			<command:commandLines>
				<command:commandLine>
					<command:commandText></command:commandText>
				</command:commandLine>
			</command:commandLines>
		</command:example>
	</command:examples>
	<maml:relatedLinks>
	</maml:relatedLinks>
</command:command>
</helpItems>